<?xml version="1.0" encoding="utf-8" ?>
<dwsync>
<file name="DSC04297.jpg" server="ftp.mptroop109.com" local="130688720605593229" remote="130224096000000000" Dst="1" />
<file name="DSC04299.jpg" server="ftp.mptroop109.com" local="130688720611893388" remote="130224096000000000" Dst="1" />
<file name="DSC04305.jpg" server="ftp.mptroop109.com" local="130688720616153954" remote="130224096000000000" Dst="1" />
<file name="DSC04302.jpg" server="ftp.mptroop109.com" local="130688720617233690" remote="130224096000000000" Dst="1" />
<file name="DSC04306.jpg" server="ftp.mptroop109.com" local="130688720620544048" remote="130224096000000000" Dst="1" />
<file name="DSC04308.jpg" server="ftp.mptroop109.com" local="130688720627214646" remote="130224096000000000" Dst="1" />
<file name="DSC04311.jpg" server="ftp.mptroop109.com" local="130688720628304555" remote="130224096000000000" Dst="1" />
<file name="DSC04313.jpg" server="ftp.mptroop109.com" local="130688720632564551" remote="130224096000000000" Dst="1" />
<file name="DSC04316.jpg" server="ftp.mptroop109.com" local="130688720635784760" remote="130224096000000000" Dst="1" />
<file name="DSC04319.jpg" server="ftp.mptroop109.com" local="130688720642165107" remote="130224096000000000" Dst="1" />
<file name="DSC04320.jpg" server="ftp.mptroop109.com" local="130688720643225378" remote="130224096000000000" Dst="1" />
<file name="DSC04321.jpg" server="ftp.mptroop109.com" local="130688720646435354" remote="130224096000000000" Dst="1" />
<file name="DSC04322.jpg" server="ftp.mptroop109.com" local="130688720652875751" remote="130224096000000000" Dst="1" />
<file name="DSC04323.jpg" server="ftp.mptroop109.com" local="130688720654936114" remote="130224096000000000" Dst="1" />
<file name="DSC04324.jpg" server="ftp.mptroop109.com" local="130688720658136130" remote="130224096000000000" Dst="1" />
<file name="DSC04326.jpg" server="ftp.mptroop109.com" local="130688720664596415" remote="130224096000000000" Dst="1" />
<file name="DSC04327.jpg" server="ftp.mptroop109.com" local="130688720666566892" remote="130224096000000000" Dst="1" />
<file name="DSC04328.jpg" server="ftp.mptroop109.com" local="130688720673057296" remote="130224096000000000" Dst="1" />
<file name="DSC04330.jpg" server="ftp.mptroop109.com" local="130688720675097005" remote="130224096000000000" Dst="1" />
<file name="DSC04331.jpg" server="ftp.mptroop109.com" local="130688720678297368" remote="130224096000000000" Dst="1" />
<file name="DSC04334.jpg" server="ftp.mptroop109.com" local="130688720684697826" remote="130224096000000000" Dst="1" />
<file name="DSC04335.jpg" server="ftp.mptroop109.com" local="130688720686737916" remote="130224096000000000" Dst="1" />
<file name="DSC04336.jpg" server="ftp.mptroop109.com" local="130688720689938183" remote="130224096000000000" Dst="1" />
<file name="DSC04337.jpg" server="ftp.mptroop109.com" local="130688720696318225" remote="130224096000000000" Dst="1" />
<file name="DSC04338.jpg" server="ftp.mptroop109.com" local="130688720700598474" remote="130224096000000000" Dst="1" />
<file name="DSC04339.jpg" server="ftp.mptroop109.com" local="130688720701658746" remote="130224096000000000" Dst="1" />
<file name="DSC04341.jpg" server="ftp.mptroop109.com" local="130688720707989133" remote="130224096000000000" Dst="1" />
<file name="DSC04342.jpg" server="ftp.mptroop109.com" local="130688720710009428" remote="130224096000000000" Dst="1" />
<file name="DSC04343.jpg" server="ftp.mptroop109.com" local="130688720716319607" remote="130224096000000000" Dst="1" />
<file name="DSC04344.jpg" server="ftp.mptroop109.com" local="130688720718359628" remote="130224096000000000" Dst="1" />
<file name="DSC04346.jpg" server="ftp.mptroop109.com" local="130688720721529907" remote="130224096000000000" Dst="1" />
<file name="image1.jpg" server="ftp.mptroop109.com" local="130688720727900268" remote="130224096000000000" Dst="1" />
<file name="image2.jpg" server="ftp.mptroop109.com" local="130688720730020384" remote="130224096000000000" Dst="1" />
</dwsync>