<?xml version="1.0" encoding="utf-8" ?>
<dwsync>
<file name="DSC07129.jpg" server="ftp.mptroop109.com" local="130688698176442877" remote="130224096000000000" Dst="1" />
<file name="DSC07130.jpg" server="ftp.mptroop109.com" local="130688698181283223" remote="130224096000000000" Dst="1" />
<file name="DSC07131.jpg" server="ftp.mptroop109.com" local="130688698197794176" remote="130224096000000000" Dst="1" />
<file name="DSC07132.jpg" server="ftp.mptroop109.com" local="130688698198884179" remote="130224096000000000" Dst="1" />
<file name="DSC07134.jpg" server="ftp.mptroop109.com" local="130688698205784418" remote="130224096000000000" Dst="1" />
<file name="DSC07137.jpg" server="ftp.mptroop109.com" local="130688698207874526" remote="130224096000000000" Dst="1" />
<file name="DSC07138.jpg" server="ftp.mptroop109.com" local="130688698217565724" remote="130224096000000000" Dst="1" />
<file name="DSC07139.jpg" server="ftp.mptroop109.com" local="130688698218785174" remote="130224096000000000" Dst="1" />
<file name="DSC07140.jpg" server="ftp.mptroop109.com" local="130688698225515798" remote="130224096000000000" Dst="1" />
<file name="DSC07141.jpg" server="ftp.mptroop109.com" local="130688698229915805" remote="130224096000000000" Dst="1" />
<file name="DSC07144.jpg" server="ftp.mptroop109.com" local="130688698231105875" remote="130224096000000000" Dst="1" />
<file name="DSC07145.jpg" server="ftp.mptroop109.com" local="130688698237976283" remote="130224096000000000" Dst="1" />
<file name="DSC07147.jpg" server="ftp.mptroop109.com" local="130688698240016708" remote="130224096000000000" Dst="1" />
<file name="DSC07148.jpg" server="ftp.mptroop109.com" local="130688698258917705" remote="130224096000000000" Dst="1" />
<file name="DSC07154.jpg" server="ftp.mptroop109.com" local="130688698260067527" remote="130224096000000000" Dst="1" />
<file name="DSC07153.jpg" server="ftp.mptroop109.com" local="130688698263658158" remote="130224096000000000" Dst="1" />
</dwsync>